aitv/__init__.py
aitv/aitv.py
aitv-0.0.2.dist-info/METADATA
aitv-0.0.2.dist-info/WHEEL
aitv-0.0.2.dist-info/top_level.txt
aitv-0.0.2.dist-info/RECORD
