Metadata-Version: 2.1
Name: aitv
Version: 0.0.2
Summary: A basic python script to merge an audio and an image into a video using ffmpeg.
Home-page: UNKNOWN
Author: JustCow
Author-email: <justcow@pm.me>
License: UNKNOWN
Keywords: python,video,audio,justcow
Platform: UNKNOWN
Classifier: Programming Language :: Python :: 3
Classifier: Operating System :: Unix
Classifier: Operating System :: MacOS :: MacOS X
Classifier: Operating System :: Microsoft :: Windows
Requires-Dist: ffmpeg-python
